MANIFEST.in
README.rst
setup.py
bhand/__init__.py
bhand/_version.py
bhand/cli.py
bhand/sim.py
bhand.egg-info/PKG-INFO
bhand.egg-info/SOURCES.txt
bhand.egg-info/dependency_links.txt
bhand.egg-info/entry_points.txt
bhand.egg-info/requires.txt
bhand.egg-info/top_level.txt
tests/test_cli.py
tests/test_sim.py