Metadata-Version: 1.1
Name: bhand
Version: 0.1.0
Summary: command-line interface and Python package for the Brunel Hand by Open Bionics
Home-page: https://github.com/rerobots/brunel_hand_cli
Author: Scott C. Livingston
Author-email: UNKNOWN
License: UNKNOWN
Platform: UNKNOWN
Classifier: License :: OSI Approved :: Apache Software License
Classifier: Programming Language :: Python :: 2.7
Classifier: Programming Language :: Python :: 3
Classifier: Programming Language :: Python :: 3.4
Classifier: Programming Language :: Python :: 3.5
Classifier: Programming Language :: Python :: 3.6
